pydeckout
