Metadata-Version: 1.1
Name: pydeckout
Version: 0.0.2
Summary: A quick and dirty dependency filler
Home-page: https://github.com/vchynarov/pydeckout
Author: Viktor Chynarov
Author-email: viktor.chynarov@gmail.com
License: MIT
Keywords: decorator class methods customization functional
Platform: UNKNOWN
Classifier: Development Status :: 3 - Alpha
Classifier: Intended Audience :: Developers
Classifier: Topic :: Software Development :: Build Tools
Classifier: License :: OSI Approved :: MIT License
Classifier: Programming Language :: Python :: 2.6
Classifier: Programming Language :: Python :: 2.7
